wxyz/json_schema_form/__init__.py
wxyz/json_schema_form/_version.py
wxyz/json_schema_form/base.py
wxyz/json_schema_form/install.json
wxyz/json_schema_form/widget_json_schema_form.py
wxyz/json_schema_form/js/LICENSE.txt
wxyz/json_schema_form/js/README.md
wxyz/json_schema_form/js/package.json
wxyz/json_schema_form/labextension/package.json
wxyz/json_schema_form/labextension/static/129.7fac6bf7fb8d29fbfe00.js
wxyz/json_schema_form/labextension/static/195.bddbb1b2d8c490417991.js
wxyz/json_schema_form/labextension/static/266.cd30d5a8a400522af8bb.js
wxyz/json_schema_form/labextension/static/289.d5656567f3a6d3189808.js
wxyz/json_schema_form/labextension/static/333.03cf7fce9d872b13bb6a.js
wxyz/json_schema_form/labextension/static/522.ed2baddbbca7823a2ed3.js
wxyz/json_schema_form/labextension/static/568.5c1cfab915eb1fa5ae79.js
wxyz/json_schema_form/labextension/static/713.d31ddf08dd5151b7fd3b.js
wxyz/json_schema_form/labextension/static/713.d31ddf08dd5151b7fd3b.js.LICENSE.txt
wxyz/json_schema_form/labextension/static/738.94aca03d38deb39ebd81.js
wxyz/json_schema_form/labextension/static/781.50a7569c34b2bfd80a01.js
wxyz/json_schema_form/labextension/static/81.8612744e3a2082ded9cc.js
wxyz/json_schema_form/labextension/static/82.b5bd357cc07741ec7801.js
wxyz/json_schema_form/labextension/static/91.cd1bc91b1a111852f82c.js
wxyz/json_schema_form/labextension/static/remoteEntry.9f08c738aa518e5e27c2.js
wxyz/json_schema_form/labextension/static/style.js
wxyz_json_schema_form-0.5.1.data/data/share/jupyter/labextensions/@deathbeds/wxyz-json-schema-form/install.json
wxyz_json_schema_form-0.5.1.data/data/share/jupyter/labextensions/@deathbeds/wxyz-json-schema-form/package.json
wxyz_json_schema_form-0.5.1.data/data/share/jupyter/labextensions/@deathbeds/wxyz-json-schema-form/static/129.7fac6bf7fb8d29fbfe00.js
wxyz_json_schema_form-0.5.1.data/data/share/jupyter/labextensions/@deathbeds/wxyz-json-schema-form/static/195.bddbb1b2d8c490417991.js
wxyz_json_schema_form-0.5.1.dist-info/LICENSE.txt
wxyz_json_schema_form-0.5.1.dist-info/METADATA
wxyz_json_schema_form-0.5.1.dist-info/WHEEL
wxyz_json_schema_form-0.5.1.dist-info/top_level.txt
wxyz_json_schema_form-0.5.1.dist-info/RECORD
