Metadata-Version: 2.1
Name: wxyz-json-schema-form
Version: 0.5.1
Summary: experimental Jupyter widgets for JSON Schema Form
Home-page: https://deathbeds.github.io/wxyz
Author: wxyz contributors
Author-email: ripxl@googlegroups.com
License: BSD-3-Clause
Project-URL: Bug Tracker, https://github.com/deathbeds/wxyz/issues
Project-URL: Changelog, https://github.com/deathbeds/wxyz/blob/master/CHANGELOG.md
Project-URL: CI, https://dev.azure.com/nickbollweg/deathbeds/_build/latest?definitionId=6&branchName=master
Project-URL: Documentation, https://deathbeds.github.io/wxyz
Project-URL: Releases, https://github.com/deathbeds/wxyz/releases
Project-URL: Source Code, https://github.com/deathbeds/wxyz
Keywords: Interactive
Platform: UNKNOWN
Classifier: Framework :: Jupyter
Classifier: Intended Audience :: Developers
Classifier: Intended Audience :: Information Technology
Classifier: License :: OSI Approved :: BSD License
Classifier: Programming Language :: Python
Requires-Python: >=3.7
License-File: src/wxyz/json_schema_form/js/LICENSE.txt
Requires-Dist: wxyz-core (<0.6,>=0.5)
